builders/MobileDriverDetailsBuilder.py
builders/ScenarioBuilder.py
builders/SmartBotBuilder.py
builders/TestCaseBuilder.py
builders/__init__.py
listeners/SuiteListener.py
listeners/TestListener.py
listeners/__init__.py
mdb/__init__.py
mdb/android/ADB.py
mdb/android/Android.py
mdb/android/DumpSysParser.py
mdb/android/__init__.py
mdb/builder/DeviceDetailBuilder.py
mdb/builder/__init__.py
mdb/core/CommandExecutor.py
mdb/core/MDB.py
mdb/core/Mobile.py
mdb/core/__init__.py
mdb/exceptions/ConnectedDevicesException.py
mdb/exceptions/UnsupportedPlatformException.py
mdb/exceptions/__init__.py
mdb/helpers/AndroidHelper.py
mdb/helpers/IOSHelper.py
mdb/helpers/__init__.py
mdb/ios/DumpsysParser.py
mdb/ios/IDB.py
mdb/ios/IOS.py
mdb/ios/__init__.py
mdb/utils/Commands.py
mdb/utils/__init__.py
model/AttributeDict.py
model/Attributes.py
model/__init__.py
monitor/__init__.py
monitor/builder/MonitoringDetailsBuilder.py
monitor/builder/__init__.py
monitor/clients/BuildsClient.py
monitor/clients/DeviceClient.py
monitor/clients/IntellisenseClient.py
monitor/clients/ScenariosClient.py
monitor/clients/__init__.py
monitor/constants/MongoDB.py
monitor/constants/__init__.py
monitor/entities/CpuData.py
monitor/entities/CrashData.py
monitor/entities/DeviceDetails.py
monitor/entities/ErrorResponse.py
monitor/entities/Intellisense.py
monitor/entities/MemoryData.py
monitor/entities/MongoService.py
monitor/entities/MonitoringDetails.py
monitor/entities/OptimusConfiguration.py
monitor/entities/RunConfiguration.py
monitor/entities/ScenarioTimeline.py
monitor/entities/ScreenshotStatistics.py
monitor/entities/SmartBOT.py
monitor/entities/TestCase.py
monitor/entities/TestFeedDetails.py
monitor/entities/__init__.py
monitor/entities/Device/DeviceType.py
monitor/entities/Device/Platform.py
monitor/entities/Device/Status.py
monitor/entities/Device/__init__.py
monitor/entities/performance/Activity.py
monitor/entities/performance/CpuStatistics.py
monitor/entities/performance/Exceptions.py
barbareeka_engine_python-0.0.95.dist-info/METADATA
barbareeka_engine_python-0.0.95.dist-info/WHEEL
barbareeka_engine_python-0.0.95.dist-info/top_level.txt
barbareeka_engine_python-0.0.95.dist-info/RECORD
