Metadata-Version: 2.1
Name: barbareeka-engine-python
Version: 0.0.95
Summary: barbareeka-client for optimusCloud reporting engine
Home-page: https://gitlab.com/testvagrant/optimus-pleiades/optimus-cloud/barbareeka-engine-python
Author: Nishant Sharma
Author-email: thenishant3@gmail.com
License: UNKNOWN
Platform: UNKNOWN
Classifier: Programming Language :: Python :: 3
Classifier: License :: OSI Approved :: MIT License
Classifier: Operating System :: OS Independent
Requires-Python: >=3.6
